ACKNOWLEDGEMENTS.md
ARCHITECTURE.md
CHANGELOG.md
CODING_STANDARD.md
CONTRIBUTING.md
EXTENDING.md
FAQ.md
LICENSE
MANIFEST.in
README.md
SECURITY.md
pyproject.toml
setup.cfg
setup.py
hug/__init__.py
hug/__main__.py
hug/_empty.py
hug/_version.py
hug/api.py
hug/authentication.py
hug/decorators.py
hug/defaults.py
hug/development_runner.py
hug/directives.py
hug/exceptions.py
hug/format.py
hug/input_format.py
hug/interface.py
hug/introspect.py
hug/json_module.py
hug/middleware.py
hug/output_format.py
hug/redirect.py
hug/route.py
hug/routing.py
hug/store.py
hug/test.py
hug/this.py
hug/transform.py
hug/types.py
hug/use.py
hug/validate.py
hug_upgraded.egg-info/PKG-INFO
hug_upgraded.egg-info/SOURCES.txt
hug_upgraded.egg-info/dependency_links.txt
hug_upgraded.egg-info/entry_points.txt
hug_upgraded.egg-info/requires.txt
hug_upgraded.egg-info/top_level.txt
tests/test_api.py
tests/test_async.py
tests/test_authentication.py
tests/test_context_factory.py
tests/test_decorators.py
tests/test_directives.py
tests/test_documentation.py
tests/test_exceptions.py
tests/test_full_request.py
tests/test_global_context.py
tests/test_input_format.py
tests/test_interface.py
tests/test_introspect.py
tests/test_main.py
tests/test_middleware.py
tests/test_output_format.py
tests/test_redirect.py
tests/test_route.py
tests/test_routing.py
tests/test_store.py
tests/test_test.py
tests/test_this.py
tests/test_transform.py
tests/test_types.py
tests/test_use.py
tests/test_validate.py