Metadata-Version: 2.4
Name: hug-upgraded
Version: 2.7.1
Summary: (🍴Fork for newer Python version compatibility) A Python framework that makes developing APIs as simple as possible, but no simpler 
Home-page: https://github.com/comaintain/hug
Author: Timothy Crosley
Author-email: timothy.crosley@gmail.com
License: MIT
Project-URL: Documentation, http://www.hug.rest/
Keywords: Web,Python,Python3,Refactoring,REST,Framework,RPC
Classifier: Development Status :: 6 - Mature
Classifier: Intended Audience :: Developers
Classifier: Natural Language :: English
Classifier: Environment :: Console
Classifier: License :: OSI Approved :: MIT License
Classifier: Programming Language :: Python
Classifier: Programming Language :: Python :: 3
Classifier: Programming Language :: Python :: 3.5
Classifier: Programming Language :: Python :: 3.6
Classifier: Programming Language :: Python :: 3.7
Classifier: Programming Language :: Python :: 3.8
Classifier: Programming Language :: Python :: 3.9
Classifier: Programming Language :: Python :: 3.10
Classifier: Programming Language :: Python :: 3.11
Classifier: Programming Language :: Python :: 3.12
Classifier: Programming Language :: Python :: 3.13
Classifier: Programming Language :: Python :: 3.14
Classifier: Topic :: Software Development :: Libraries
Classifier: Topic :: Utilities
Requires: falcon
Requires: requests
Requires-Python: >=3.5
License-File: LICENSE
Requires-Dist: falcon==2.0.0
Requires-Dist: requests
Requires-Dist: packaging
Requires-Dist: legacy-cgi; python_version >= "3.13"
Dynamic: author
Dynamic: author-email
Dynamic: classifier
Dynamic: description
Dynamic: description-content-type
Dynamic: home-page
Dynamic: keywords
Dynamic: license
Dynamic: license-file
Dynamic: project-url
Dynamic: requires
Dynamic: requires-dist
Dynamic: requires-python
Dynamic: summary
